.coveragerc
.travis.yml
AUTHORS.rst
CHANGELOG.rst
LICENSE
MANIFEST.in
README.rst
dev-requirements.txt
requirements.txt
setup.cfg
setup.py
tox.ini
docs/Makefile
docs/api.rst
docs/changelog.rst
docs/conf.py
docs/examples.rst
docs/index.rst
docs/license.rst
docs/make.bat
docs/release_procedure.rst
docs/wishlist.rst
docs/_static/.dummy
src/charticle/__init__.py
src/charticle/_validators.py
src/charticle/hierarchy.py
src/charticle/venn.py
src/charticle.egg-info/PKG-INFO
src/charticle.egg-info/SOURCES.txt
src/charticle.egg-info/dependency_links.txt
src/charticle.egg-info/not-zip-safe
src/charticle.egg-info/requires.txt
src/charticle.egg-info/top_level.txt
tests/test_validators.py