Metadata-Version: 1.1
Name: charticle
Version: 0.0.3
Summary: Charticle combines best (worst?) of charts and articles.
Home-page: https://charticle.readthedocs.io/
Author: Jeremy G. Kahn
Author-email: jeremy@trochee.net
License: MIT
Keywords: chart,labels,thinkpiece
Platform: UNKNOWN
Classifier: Development Status :: 3 - Alpha
Classifier: Intended Audience :: Developers
Classifier: Intended Audience :: Science/Research
Classifier: Natural Language :: English
Classifier: License :: OSI Approved :: MIT License
Classifier: Operating System :: OS Independent
Classifier: Programming Language :: Python
Classifier: Programming Language :: Python :: 2
Classifier: Programming Language :: Python :: 2.7
Classifier: Programming Language :: Python :: 3
Classifier: Programming Language :: Python :: 3.5
Classifier: Topic :: Multimedia :: Graphics :: Presentation
Classifier: Topic :: Scientific/Engineering :: Visualization
